collective.js.galleria-1.7.0-py3.10-nspkg.pth
collective/js/galleria/__init__.py
collective/js/galleria/browser.zcml
collective/js/galleria/configure.zcml
collective/js/galleria/interfaces.py
collective/js/galleria/profiles.zcml
collective/js/galleria/setuphandlers.py
collective/js/galleria/testing.py
collective/js/galleria/profiles/default/browserlayer.xml
collective/js/galleria/profiles/default/metadata.xml
collective/js/galleria/profiles/default/registry/jsregistry.xml
collective/js/galleria/profiles/uninstall/browserlayer.xml
collective/js/galleria/profiles/uninstall/registry/jsregistry.xml
collective/js/galleria/resources/galleria.classic.test.js
collective/js/galleria/resources/galleria.js
collective/js/galleria/resources/galleria.min.js
collective/js/galleria/resources/package.json
collective/js/galleria/resources/yarn.lock
collective/js/galleria/resources/images/classic-loader.gif
collective/js/galleria/resources/images/classic-map.png
collective/js/galleria/resources/plugins/flickr/demo.html
collective/js/galleria/resources/plugins/flickr/galleria.flickr.js
collective/js/galleria/resources/plugins/flickr/galleria.flickr.min.js
collective/js/galleria/resources/plugins/history/demo.html
collective/js/galleria/resources/plugins/history/galleria.history.js
collective/js/galleria/resources/plugins/history/galleria.history.min.js
collective/js/galleria/resources/themes/azur/demo-cdn.html
collective/js/galleria/resources/themes/azur/demo-retina.html
collective/js/galleria/resources/themes/azur/demo.html
collective/js/galleria/resources/themes/azur/galleria.azur.css
collective/js/galleria/resources/themes/azur/galleria.azur.js
collective/js/galleria/resources/themes/azur/galleria.azur.min.css
collective/js/galleria/resources/themes/azur/galleria.azur.min.js
collective/js/galleria/resources/themes/classic/demo-cdn.html
collective/js/galleria/resources/themes/classic/demo-retina.html
collective/js/galleria/resources/themes/classic/demo.html
collective_js_galleria-1.7.0.dist-info/LICENSE.GPL
collective_js_galleria-1.7.0.dist-info/LICENSE.rst
collective_js_galleria-1.7.0.dist-info/METADATA
collective_js_galleria-1.7.0.dist-info/WHEEL
collective_js_galleria-1.7.0.dist-info/entry_points.txt
collective_js_galleria-1.7.0.dist-info/namespace_packages.txt
collective_js_galleria-1.7.0.dist-info/top_level.txt
collective_js_galleria-1.7.0.dist-info/RECORD
