Metadata-Version: 2.2
Name: collective.js.galleria
Version: 1.7.0
Summary: Register Galleria JQuery plugin in Plone
Home-page: https://github.com/collective/collective.js.galleria
Author: JeanMichel FRANCOIS aka toutpt
Author-email: toutpt@gmail.com
License: GPL version 2
Project-URL: PyPI, https://pypi.python.org/pypi/collective.js.galleria
Project-URL: Source, https://github.com/collective/collective.js.galleria
Project-URL: Tracker, https://github.com/collective/collective.js.galleria/issues
Keywords: Python Plone CMS
Classifier: Development Status :: 5 - Production/Stable
Classifier: Environment :: Web Environment
Classifier: Framework :: Plone
Classifier: Framework :: Plone :: Addon
Classifier: Framework :: Plone :: 5.2
Classifier: Programming Language :: Python
Classifier: Programming Language :: Python :: 3
Classifier: Programming Language :: Python :: 3.7
Classifier: Programming Language :: Python :: 3.8
Classifier: Operating System :: OS Independent
Classifier: Topic :: Internet :: WWW/HTTP
Classifier: Topic :: Software Development :: Libraries :: Python Modules
Requires-Python: >=3.7
License-File: LICENSE.GPL
License-File: LICENSE.rst
Requires-Dist: setuptools
Requires-Dist: plone.app.registry
Requires-Dist: plone.resource
Requires-Dist: Products.CMFPlone>=5.2
Provides-Extra: test
Requires-Dist: plone.app.robotframework[debug]; extra == "test"
Requires-Dist: plone.app.testing; extra == "test"
Requires-Dist: plone.testing; extra == "test"
Requires-Dist: zope.component; extra == "test"
Requires-Dist: zope.configuration; extra == "test"
Dynamic: author
Dynamic: author-email
Dynamic: classifier
Dynamic: description
Dynamic: home-page
Dynamic: keywords
Dynamic: license
Dynamic: project-url
Dynamic: provides-extra
Dynamic: requires-dist
Dynamic: requires-python
Dynamic: summary
